python_humble_utils/__init__.py
python_humble_utils/classes.py
python_humble_utils/filesystem.py
python_humble_utils/objects.py
python_humble_utils/strings.py
python_humble_utils-3.1.0.dist-info/AUTHORS.rst
python_humble_utils-3.1.0.dist-info/LICENSE
python_humble_utils-3.1.0.dist-info/METADATA
python_humble_utils-3.1.0.dist-info/WHEEL
python_humble_utils-3.1.0.dist-info/top_level.txt
python_humble_utils-3.1.0.dist-info/RECORD
