Metadata-Version: 2.1
Name: python-humble-utils
Version: 3.1.0
Summary: Python utils for everyday use.
Home-page: https://github.com/webyneter/python-humble-utils
Author: Nikita P. Shupeyko
Author-email: webyneter@gmail.com
License: MIT
Keywords: python,humble,utility,utilities,util,utils,helper,helpers
Platform: UNKNOWN
Classifier: Development Status :: 5 - Production/Stable
Classifier: Intended Audience :: Developers
Classifier: License :: OSI Approved :: MIT License
Classifier: Natural Language :: English
Classifier: Programming Language :: Python :: 3
Classifier: Programming Language :: Python :: 3.6
Classifier: Programming Language :: Python :: 3.7
Classifier: Programming Language :: Python :: 3.8
